dataplaneapi/__init__.py
dataplaneapi/api_client.py
dataplaneapi/configuration.py
dataplaneapi/rest.py
dataplaneapi/api/__init__.py
dataplaneapi/api/acl_api.py
dataplaneapi/api/acl_runtime_api.py
dataplaneapi/api/backend_api.py
dataplaneapi/api/backend_switching_rule_api.py
dataplaneapi/api/bind_api.py
dataplaneapi/api/cache_api.py
dataplaneapi/api/cluster_api.py
dataplaneapi/api/configuration_api.py
dataplaneapi/api/declare_capture_api.py
dataplaneapi/api/defaults_api.py
dataplaneapi/api/dgram_bind_api.py
dataplaneapi/api/discovery_api.py
dataplaneapi/api/fcgi_app_api.py
dataplaneapi/api/filter_api.py
dataplaneapi/api/frontend_api.py
dataplaneapi/api/global_api.py
dataplaneapi/api/group_api.py
dataplaneapi/api/health_api.py
dataplaneapi/api/http_after_response_rule_api.py
dataplaneapi/api/http_check_api.py
dataplaneapi/api/http_error_rule_api.py
dataplaneapi/api/http_errors_api.py
dataplaneapi/api/http_request_rule_api.py
dataplaneapi/api/http_response_rule_api.py
dataplaneapi/api/information_api.py
dataplaneapi/api/log_forward_api.py
dataplaneapi/api/log_target_api.py
dataplaneapi/api/mailer_entry_api.py
dataplaneapi/api/mailers_api.py
dataplaneapi/api/maps_api.py
dataplaneapi/api/nameserver_api.py
dataplaneapi/api/peer_api.py
dataplaneapi/api/peer_entry_api.py
dataplaneapi/api/process_manager_api.py
dataplaneapi/api/reloads_api.py
dataplaneapi/api/resolver_api.py
dataplaneapi/api/ring_api.py
dataplaneapi/api/server_api.py
dataplaneapi/api/server_switching_rule_api.py
dataplaneapi/api/server_template_api.py
dataplaneapi/api/service_discovery_api.py
dataplaneapi/api/sites_api.py
dataplaneapi/api/specification_api.py
dataplaneapi/api/specification_openapiv3_api.py
dataplaneapi/api/spoe_api.py
dataplaneapi/api/spoe_transactions_api.py
dataplaneapi/api/stats_api.py
dataplaneapi/api/stick_rule_api.py
dataplaneapi/api/stick_table_api.py
dataplaneapi/api/storage_api.py
dataplaneapi/api/tcp_check_api.py
dataplaneapi/api/tcp_request_rule_api.py
haproxy_py-0.0.2.dist-info/LICENSE
haproxy_py-0.0.2.dist-info/METADATA
haproxy_py-0.0.2.dist-info/WHEEL
haproxy_py-0.0.2.dist-info/top_level.txt
haproxy_py-0.0.2.dist-info/RECORD
