Metadata-Version: 2.1
Name: haproxy-py
Version: 0.0.2
Summary: HAProxy Data Plane API
Home-page: 
Author-email: support@haproxy.com
License: UNKNOWN
Keywords: Swagger,HAProxy Data Plane API
Platform: UNKNOWN
License-File: LICENSE
Requires-Dist: urllib3 (>=1.15)
Requires-Dist: six (>=1.10)
Requires-Dist: certifi
Requires-Dist: python-dateutil
